{
	"info": {
		"_postman_id": "9c13528e-c4be-40db-b1cc-5bb63940fae6",
		"name": "Family Finance",
		"schema": "https://schema.getpostman.com/json/collection/v2.1.0/collection.json"
	},
	"item": [
		{
			"name": "Expenses",
			"item": [
				{
					"name": "ADD",
					"request": {
						"method": "POST",
						"header": [
							{
								"description": "\n",
								"key": "Content-Type",
								"name": "Content-Type",
								"type": "text",
								"value": "application/json"
							}
						],
						"body": {
							"mode": "raw",
							"raw": "{\n   \"description\": \"gasto no motel <3\",\n   \"createdBy\": 1,\n   \"value\": 113.50,\n   \"categoryId\": 1\n}",
							"options": {
								"raw": {
									"language": "json"
								}
							}
						},
						"url": {
							"raw": "localhost:8080/api/v1/expenses/",
							"host": [
								"localhost"
							],
							"port": "8080",
							"path": [
								"api",
								"v1",
								"expenses",
								""
							]
						}
					},
					"response": []
				},
				{
					"name": "UPDATE",
					"request": {
						"method": "PUT",
						"header": [
							{
								"description": "\n",
								"key": "Content-Type",
								"name": "Content-Type",
								"type": "text",
								"value": "application/json"
							}
						],
						"body": {
							"mode": "raw",
							"raw": "{\n   \"id\": 4,\n   \"description\": \"abc\",\n   \"createdBy\": 1,\n   \"value\": 113.50,\n   \"categoryId\": 1\n}",
							"options": {
								"raw": {
									"language": "json"
								}
							}
						},
						"url": {
							"raw": "localhost:8282/api/v1/expenses/4",
							"host": [
								"localhost"
							],
							"port": "8282",
							"path": [
								"api",
								"v1",
								"expenses",
								"4"
							]
						}
					},
					"response": []
				},
				{
					"name": "GET ALL",
					"request": {
						"method": "GET",
						"header": [],
						"url": {
							"raw": "localhost:8282/api/v1/expenses/",
							"host": [
								"localhost"
							],
							"port": "8282",
							"path": [
								"api",
								"v1",
								"expenses",
								""
							]
						}
					},
					"response": []
				},
				{
					"name": "GET BY ID",
					"request": {
						"method": "GET",
						"header": [],
						"url": {
							"raw": "localhost:8080/api/v1/expenses/1",
							"host": [
								"localhost"
							],
							"port": "8080",
							"path": [
								"api",
								"v1",
								"expenses",
								"1"
							]
						}
					},
					"response": []
				},
				{
					"name": "GET ALL BY ID USER",
					"request": {
						"method": "GET",
						"header": [],
						"url": {
							"raw": "localhost:8282/api/v1/expenses/findAllByIdUser/",
							"host": [
								"localhost"
							],
							"port": "8282",
							"path": [
								"api",
								"v1",
								"expenses",
								"findAllByIdUser",
								""
							]
						}
					},
					"response": []
				},
				{
					"name": "DELETE",
					"request": {
						"method": "DELETE",
						"header": [],
						"url": {
							"raw": "localhost:8080/api/v1/expenses/1",
							"host": [
								"localhost"
							],
							"port": "8080",
							"path": [
								"api",
								"v1",
								"expenses",
								"1"
							]
						}
					},
					"response": []
				}
			],
			"event": [
				{
					"listen": "prerequest",
					"script": {
						"id": "98e8cbce-51df-4569-8334-29c50105dae8",
						"type": "text/javascript",
						"exec": [
							""
						]
					}
				},
				{
					"listen": "test",
					"script": {
						"id": "4a09cc61-a798-422d-8a4a-68602b2c84c4",
						"type": "text/javascript",
						"exec": [
							""
						]
					}
				}
			],
			"protocolProfileBehavior": {}
		},
		{
			"name": "User",
			"item": [
				{
					"name": "ADD",
					"request": {
						"method": "POST",
						"header": [
							{
								"description": "\n",
								"key": "Content-Type",
								"name": "Content-Type",
								"type": "text",
								"value": "application/json"
							}
						],
						"body": {
							"mode": "raw",
							"raw": "{\n   \"name\": \"teste da silva\",\n   \"email\": \"teste@test\"\n}",
							"options": {
								"raw": {
									"language": "json"
								}
							}
						},
						"url": {
							"raw": "localhost:8282/api/v1/user/",
							"host": [
								"localhost"
							],
							"port": "8282",
							"path": [
								"api",
								"v1",
								"user",
								""
							]
						}
					},
					"response": []
				},
				{
					"name": "UPDATE",
					"request": {
						"method": "PUT",
						"header": [
							{
								"description": "\n",
								"key": "Content-Type",
								"name": "Content-Type",
								"type": "text",
								"value": "application/json"
							}
						],
						"body": {
							"mode": "raw",
							"raw": "{\n   \"id\": 2,\n   \"name\": \"teste da silva santos\",\n   \"email\": \"teste@test\"\n}",
							"options": {
								"raw": {
									"language": "json"
								}
							}
						},
						"url": {
							"raw": "localhost:8282/api/v1/user/2",
							"host": [
								"localhost"
							],
							"port": "8282",
							"path": [
								"api",
								"v1",
								"user",
								"2"
							]
						}
					},
					"response": []
				},
				{
					"name": "GET ALL",
					"request": {
						"method": "GET",
						"header": [],
						"url": {
							"raw": "localhost:8282/api/v1/user/",
							"host": [
								"localhost"
							],
							"port": "8282",
							"path": [
								"api",
								"v1",
								"user",
								""
							]
						}
					},
					"response": []
				},
				{
					"name": "GET BY ID",
					"request": {
						"method": "GET",
						"header": [],
						"url": {
							"raw": "localhost:8282/api/v1/user/1",
							"host": [
								"localhost"
							],
							"port": "8282",
							"path": [
								"api",
								"v1",
								"user",
								"1"
							]
						}
					},
					"response": []
				},
				{
					"name": "DELETE",
					"request": {
						"method": "DELETE",
						"header": [],
						"url": {
							"raw": "localhost:8282/api/v1/user/1",
							"host": [
								"localhost"
							],
							"port": "8282",
							"path": [
								"api",
								"v1",
								"user",
								"1"
							]
						}
					},
					"response": []
				}
			],
			"event": [
				{
					"listen": "prerequest",
					"script": {
						"id": "c98e23f2-47ae-43b8-8d04-4ec9a3bb0bf6",
						"type": "text/javascript",
						"exec": [
							""
						]
					}
				},
				{
					"listen": "test",
					"script": {
						"id": "8c50f9be-5e5e-497f-95b8-891a50390dea",
						"type": "text/javascript",
						"exec": [
							""
						]
					}
				}
			],
			"protocolProfileBehavior": {}
		}
	],
	"event": [
		{
			"listen": "prerequest",
			"script": {
				"id": "4e1a71c2-f535-4936-9bba-d8b6614599b4",
				"type": "text/javascript",
				"exec": [
					""
				]
			}
		},
		{
			"listen": "test",
			"script": {
				"id": "43595dfd-e4b8-4f1f-8f0d-bd7640928a88",
				"type": "text/javascript",
				"exec": [
					""
				]
			}
		}
	],
	"protocolProfileBehavior": {}
}